sixtyfour/__init__.py
sixtyfour/cli.py
sixtyfour/sixtyfour.py
sixtyfour-1.0.1.dist-info/LICENSE
sixtyfour-1.0.1.dist-info/METADATA
sixtyfour-1.0.1.dist-info/WHEEL
sixtyfour-1.0.1.dist-info/entry_points.txt
sixtyfour-1.0.1.dist-info/top_level.txt
sixtyfour-1.0.1.dist-info/RECORD
