Metadata-Version: 2.1
Name: sixtyfour
Version: 1.0.1
Summary: UNKNOWN
Home-page: https://github.com/kennell/sixtyfour
Author: Kevin Kennell
Author-email: kevin@kennell.de
License: MIT
Platform: UNKNOWN
Requires-Dist: click
